kikuchipy/__init__.py
kikuchipy/__init__.pyi
kikuchipy/constants.py
kikuchipy/hyperspy_extension.yaml
kikuchipy/logging.py
kikuchipy/_utils/__init__.py
kikuchipy/_utils/__init__.pyi
kikuchipy/_utils/_transfer_axes.py
kikuchipy/_utils/deprecated.py
kikuchipy/_utils/exceptions.py
kikuchipy/_utils/numba.py
kikuchipy/_utils/vector.py
kikuchipy/data/__init__.py
kikuchipy/data/__init__.pyi
kikuchipy/data/_data.py
kikuchipy/data/_registry.py
kikuchipy/data/_dummy_files/bruker_h5ebsd.py
kikuchipy/data/_dummy_files/oxford_h5ebsd.py
kikuchipy/data/edax_binary/create_dummy_edax_binary_file.py
kikuchipy/data/edax_binary/edax_binary.up1
kikuchipy/data/edax_binary/edax_binary.up2
kikuchipy/data/edax_h5ebsd/patterns.h5
kikuchipy/data/emsoft_ebsd/EBSD_TEST_Ni.h5
kikuchipy/data/emsoft_ebsd/create_dummy_emsoft_ebsd_file.py
kikuchipy/data/emsoft_ebsd/simulated_ebsd.h5
kikuchipy/data/emsoft_ebsd_master_pattern/BetheParameters.nml
kikuchipy/data/emsoft_ebsd_master_pattern/convert_emsoft_ebsd_masterpattern_file_uint8_gzip.py
kikuchipy/data/emsoft_ebsd_master_pattern/create_dummy_emsoft_ebsd_master_pattern_file.py
kikuchipy/data/emsoft_ebsd_master_pattern/master_patterns.h5
kikuchipy/data/emsoft_ebsd_master_pattern/ni.xtal
kikuchipy/data/emsoft_ebsd_master_pattern/ni_ebsdmaster.nml
kikuchipy/data/emsoft_ebsd_master_pattern/ni_mc.out
kikuchipy/data/emsoft_ebsd_master_pattern/ni_mc_mp_20kv_uint8_gzip_opts9.h5
kikuchipy/data/emsoft_ebsd_master_pattern/ni_mcopencl.nml
kikuchipy/data/emsoft_ebsd_master_pattern/ni_mp.out
kikuchipy/data/kikuchipy_h5ebsd/patterns.h5
kikuchipy/data/kikuchipy_h5ebsd/patterns_nochunks.h5
kikuchipy/data/nordif/Background acquisition pattern.bmp
kikuchipy/data/nordif/Background calibration pattern.bmp
"kikuchipy/data/nordif/Calibration (294,532).bmp"
"kikuchipy/data/nordif/Calibration (425,447).bmp"
kikuchipy/data/nordif/Pattern.dat
kikuchipy/data/nordif/Setting.txt
kikuchipy/data/nordif/Setting_bad1.txt
kikuchipy/data/nordif/Setting_bad2.txt
kikuchipy-0.11.3.dist-info/METADATA
kikuchipy-0.11.3.dist-info/WHEEL
kikuchipy-0.11.3.dist-info/entry_points.txt
kikuchipy-0.11.3.dist-info/licenses/LICENSE
kikuchipy-0.11.3.dist-info/RECORD
