Metadata-Version: 2.4
Name: kikuchipy
Version: 0.11.3
Summary: Processing, simulating, and indexing of electron backscatter diffraction (EBSD) patterns
Project-URL: Documentation, https://kikuchipy.org
Project-URL: Download, https://pypi.python.org/pypi/kikuchipy
Project-URL: Bug Tracker, https://github.com/pyxem/kikuchipy/issues
Project-URL: Source Code, https://github.com/pyxem/kikuchipy
Project-URL: Changelog, https://kikuchipy.org/en/stable/changelog.html
Author: kikuchipy developers
Maintainer-email: Håkon Wiik Ånes <hwaanes@gmail.com>
License:                     GNU GENERAL PUBLIC LICENSE
License-File: LICENSE
Keywords: BKD,EBSD,EBSP,SEM,backscatter kikuchi diffraction,dictionary indexing,electron backscatter diffraction,electron backscatter pattern,kikuchi pattern,scanning electron microscopy
Classifier: Development Status :: 4 - Beta
Classifier: Intended Audience :: Science/Research
Classifier: License :: OSI Approved :: GNU General Public License v3 or later (GPLv3+)
Classifier: Natural Language :: English
Classifier: Operating System :: OS Independent
Classifier: Programming Language :: Python :: 3
Classifier: Programming Language :: Python :: 3.10
Classifier: Programming Language :: Python :: 3.11
Classifier: Programming Language :: Python :: 3.12
Classifier: Topic :: Scientific/Engineering
Classifier: Topic :: Scientific/Engineering :: Physics
Requires-Python: >=3.10
Requires-Dist: dask[array]>=2021.8.1
Requires-Dist: diffpy-structure>=3
Requires-Dist: diffsims>=0.5.2
Requires-Dist: h5py>=2.10
Requires-Dist: hyperspy>=2.2
Requires-Dist: imageio
Requires-Dist: lazy-loader
Requires-Dist: matplotlib>=3.5
Requires-Dist: numba>=0.57
Requires-Dist: numpy>=1.23.0
Requires-Dist: orix>=0.12.1
Requires-Dist: pooch>=1.3.0
Requires-Dist: pyyaml
Requires-Dist: rosettasciio>=0.3.0
Requires-Dist: scikit-image>=0.16.2
Requires-Dist: scikit-learn
Requires-Dist: scipy>=1.7
Requires-Dist: tqdm>=0.5.2
Provides-Extra: all
Requires-Dist: nlopt; extra == 'all'
Requires-Dist: pyebsdindex!=0.3.1,>=0.2; extra == 'all'
Requires-Dist: pyvista; extra == 'all'
Provides-Extra: coverage
Requires-Dist: coverage>=5.0; extra == 'coverage'
Requires-Dist: pytest-cov>=2.8.1; extra == 'coverage'
Provides-Extra: dev
Requires-Dist: black[jupyter]>=23.1; extra == 'dev'
Requires-Dist: coverage>=5.0; extra == 'dev'
Requires-Dist: hatch; extra == 'dev'
Requires-Dist: isort; extra == 'dev'
Requires-Dist: memory-profiler; extra == 'dev'
Requires-Dist: nbsphinx>=0.7; extra == 'dev'
Requires-Dist: nlopt; extra == 'dev'
Requires-Dist: numpydoc; extra == 'dev'
Requires-Dist: outdated; extra == 'dev'
Requires-Dist: pre-commit>=1.16; extra == 'dev'
Requires-Dist: pydata-sphinx-theme; extra == 'dev'
Requires-Dist: pyebsdindex~=0.2; extra == 'dev'
Requires-Dist: pytest-benchmark; extra == 'dev'
Requires-Dist: pytest-cov>=2.8.1; extra == 'dev'
Requires-Dist: pytest-rerunfailures; extra == 'dev'
Requires-Dist: pytest-xdist; extra == 'dev'
Requires-Dist: pytest>=5.4; extra == 'dev'
Requires-Dist: pyvista; extra == 'dev'
Requires-Dist: sphinx-codeautolink[ipython]<0.14; extra == 'dev'
Requires-Dist: sphinx-copybutton>=0.2.5; extra == 'dev'
Requires-Dist: sphinx-design; extra == 'dev'
Requires-Dist: sphinx-gallery; extra == 'dev'
Requires-Dist: sphinx>=3.0.2; extra == 'dev'
Requires-Dist: sphinxcontrib-bibtex>=1.0; extra == 'dev'
Provides-Extra: doc
Requires-Dist: memory-profiler; extra == 'doc'
Requires-Dist: nbsphinx>=0.7; extra == 'doc'
Requires-Dist: nlopt; extra == 'doc'
Requires-Dist: numpydoc; extra == 'doc'
Requires-Dist: pydata-sphinx-theme; extra == 'doc'
Requires-Dist: pyebsdindex~=0.2; extra == 'doc'
Requires-Dist: pyvista; extra == 'doc'
Requires-Dist: sphinx-codeautolink[ipython]<0.14; extra == 'doc'
Requires-Dist: sphinx-copybutton>=0.2.5; extra == 'doc'
Requires-Dist: sphinx-design; extra == 'doc'
Requires-Dist: sphinx-gallery; extra == 'doc'
Requires-Dist: sphinx>=3.0.2; extra == 'doc'
Requires-Dist: sphinxcontrib-bibtex>=1.0; extra == 'doc'
Provides-Extra: tests
Requires-Dist: numpydoc; extra == 'tests'
Requires-Dist: pytest-benchmark; extra == 'tests'
Requires-Dist: pytest-rerunfailures; extra == 'tests'
Requires-Dist: pytest-xdist; extra == 'tests'
Requires-Dist: pytest>=5.4; extra == 'tests'
